ics_fixer/__init__.py
ics_fixer/main.py
ics_fixer-1.0.2.dist-info/licenses/LICENSE
ics_fixer-1.0.2.dist-info/WHEEL
ics_fixer-1.0.2.dist-info/entry_points.txt
ics_fixer-1.0.2.dist-info/METADATA
ics_fixer-1.0.2.dist-info/RECORD
