Metadata-Version: 2.4
Name: ics-fixer
Version: 1.0.2
Summary: Fix slightly broken iCalendar files
Keywords: icalendar,ical,ics,data-wrangling,sanitizer,datacleaning
Author: nateify
Author-email: nateify <nateify@users.noreply.github.com>
License-Expression: MIT
License-File: LICENSE
Classifier: Environment :: Console
Classifier: Operating System :: OS Independent
Classifier: Programming Language :: Python
Classifier: Programming Language :: Python :: 3
Classifier: Programming Language :: Python :: 3.13
Classifier: License :: OSI Approved :: MIT License
Classifier: Topic :: Utilities
Requires-Dist: dateparser>=1.2.2
Requires-Dist: ftfy>=6.3.1
Requires-Dist: icalendar>=6.3.1
Requires-Dist: typer-slim>=0.17.4
Requires-Python: >=3.13
Project-URL: Documentation, https://github.com/nateify/ics-fixer#readme
Project-URL: Homepage, https://github.com/nateify/ics-fixer
